zuper_zapp.pyi
zuper_zapp.cpython-310-x86_64-linux-gnu.so
zuper_zapp_z7-7.3.2202171749.dist-info/WHEEL
zuper_zapp_z7-7.3.2202171749.dist-info/top_level.txt
zuper_zapp_z7-7.3.2202171749.dist-info/RECORD
zuper_zapp_z7-7.3.2202171749.dist-info/METADATA
zuper_zapp_z7-7.3.2202171749.dist-info/zip-safe
